__init__.py
leet2git/__init__.py
leet2git/config_manager.py
leet2git/default_handler.py
leet2git/file_handler.py
leet2git/leet2git.py
leet2git/leetcode_client.py
leet2git/my_utils.py
leet2git/python_handler.py
leet2git/question_db.py
leet2git/readme_handler.py
leet2git/version.py
leet2git-0.2.1.dist-info/LICENSE
leet2git-0.2.1.dist-info/METADATA
leet2git-0.2.1.dist-info/WHEEL
leet2git-0.2.1.dist-info/entry_points.txt
leet2git-0.2.1.dist-info/top_level.txt
leet2git-0.2.1.dist-info/RECORD
