Metadata-Version: 2.1
Name: leet2git
Version: 0.2.1
Summary: Tool to ease the integration between Leetcode and a Git repository
Home-page: https://github.com/yurirocha15/leetcode2github
Author: Yuri Rocha
Author-email: yurirocha15@gmail.com
License: MIT License
Platform: UNKNOWN
Classifier: Development Status :: 2 - Pre-Alpha
Classifier: Intended Audience :: Developers
Classifier: License :: OSI Approved :: MIT License
Classifier: Natural Language :: English
Classifier: Operating System :: MacOS
Classifier: Operating System :: Microsoft :: Windows
Classifier: Operating System :: POSIX
Classifier: Operating System :: Unix
Classifier: Programming Language :: Python
Classifier: Programming Language :: Python :: 3
Classifier: Programming Language :: Python :: 3.8
Classifier: Programming Language :: Python :: 3.9
Classifier: Programming Language :: Python :: 3.10
Classifier: Topic :: Utilities
Requires-Python: >=3.8
License-File: LICENSE
Requires-Dist: appdirs (==1.4.4)
Requires-Dist: autoimport (==0.7.0)
Requires-Dist: black (==21.7b0)
Requires-Dist: beautifulsoup4 (==4.9.3)
Requires-Dist: browser-cookie3 (==0.12.1)
Requires-Dist: click (==8.0.1)
Requires-Dist: GitPython (==3.1.18)
Requires-Dist: isort (==5.9.3)
Requires-Dist: requests (==2.25.1)
Provides-Extra: dev
Requires-Dist: pre-commit (==2.8.2) ; extra == 'dev'
Requires-Dist: flake8 (==3.9.2) ; extra == 'dev'
Requires-Dist: flake8-builtins (==1.5.3) ; extra == 'dev'
Requires-Dist: flake8-docstrings (==1.5.0) ; extra == 'dev'
Requires-Dist: flake8-bugbear (==20.1.4) ; extra == 'dev'
Requires-Dist: flake8-polyfill (==1.0.2) ; extra == 'dev'
Requires-Dist: flake8-pytest (==1.3) ; extra == 'dev'
Requires-Dist: flake8-use-fstring (==1.1) ; extra == 'dev'
Requires-Dist: mypy (==0.790) ; extra == 'dev'
Requires-Dist: mypy-extensions (==0.4.3) ; extra == 'dev'
Requires-Dist: pep8-naming (==0.11.1) ; extra == 'dev'
Requires-Dist: pyflakes (==2.3.0) ; extra == 'dev'
Requires-Dist: pylint (==2.6.0) ; extra == 'dev'
Requires-Dist: pytest (==6.1.2) ; extra == 'dev'
Requires-Dist: pytest-cov (==2.10.1) ; extra == 'dev'
Requires-Dist: pytest-custom-exit-code (==0.3.0) ; extra == 'dev'
Requires-Dist: pytest-flake8 (==1.0.6) ; extra == 'dev'
Requires-Dist: pytest-mypy (==0.7.0) ; extra == 'dev'
Requires-Dist: pytest-pylint (==0.18.0) ; extra == 'dev'
